<Properties StartupConfiguration="{0AB5C353-1AAE-C112-25EE-379D5803F822}|">
  <MonoDevelop.Ide.Workbench ActiveDocument="Assets/Scripts/Movement.cs">
    <Files>
      <File FileName="Assets/Scripts/Movement.cs" Line="17" Column="6" />
    </Files>
  </MonoDevelop.Ide.Workbench>
  <MonoDevelop.Ide.DebuggingService.PinnedWatches />
  <MonoDevelop.Ide.Workspace ActiveConfiguration="Debug" />
  <MonoDevelop.Ide.ItemProperties.Assembly-CSharp PreferredExecutionTarget="b44f5bf2-8c96-4d77-9473-4f69978f93b3" />
  <MonoDevelop.Ide.DebuggingService.Breakpoints>
    <BreakpointStore />
  </MonoDevelop.Ide.DebuggingService.Breakpoints>
  <MultiItemStartupConfigurations />
</Properties>